tcgame/__init__.py
tcgame/__init__.pyi
tcgame/agents/agent.cp36-win_amd64.pyd
tcgame/agents/agent.cp37-win_amd64.pyd
tcgame/agents/agent.cp38-win_amd64.pyd
tcgame/agents/agent.cp39-win_amd64.pyd
tcgame/agents/agent.pyi
tcgame/envs/finding.cp36-win_amd64.pyd
tcgame/envs/finding.cp37-win_amd64.pyd
tcgame/envs/finding.cp38-win_amd64.pyd
tcgame/envs/finding.cp39-win_amd64.pyd
tcgame/envs/finding.pyi
tcgame/envs/flappy.cp36-win_amd64.pyd
tcgame/envs/flappy.cp37-win_amd64.pyd
tcgame/envs/flappy.cp38-win_amd64.pyd
tcgame/envs/flappy.cp39-win_amd64.pyd
tcgame/envs/flappy.pyi
tcgame/envs/path_finding.cp36-win_amd64.pyd
tcgame/envs/path_finding.cp37-win_amd64.pyd
tcgame/envs/path_finding.cp38-win_amd64.pyd
tcgame/envs/path_finding.cp39-win_amd64.pyd
tcgame/envs/path_finding.pyi
tcgame/envs/path_finding_2d.cp36-win_amd64.pyd
tcgame/envs/path_finding_2d.cp37-win_amd64.pyd
tcgame/envs/path_finding_2d.cp38-win_amd64.pyd
tcgame/envs/path_finding_2d.cp39-win_amd64.pyd
tcgame/envs/path_finding_2d.pyi
tcgame/envs/assets/flag.png
tcgame/envs/assets/flappy.ico
tcgame/envs/assets/player.png
tcgame/envs/assets/audio/die.ogg
tcgame/envs/assets/audio/die.wav
tcgame/envs/assets/audio/hit.ogg
tcgame/envs/assets/audio/hit.wav
tcgame/envs/assets/audio/point.ogg
tcgame/envs/assets/audio/point.wav
tcgame/envs/assets/audio/swoosh.ogg
tcgame/envs/assets/audio/swoosh.wav
tcgame/envs/assets/audio/wing.ogg
tcgame/envs/assets/audio/wing.wav
tcgame/envs/assets/sprites/0.png
tcgame/envs/assets/sprites/1.png
tcgame/envs/assets/sprites/2.png
tcgame/envs/assets/sprites/3.png
tcgame/envs/assets/sprites/4.png
tcgame/envs/assets/sprites/5.png
tcgame/envs/assets/sprites/6.png
tcgame/envs/assets/sprites/7.png
tcgame/envs/assets/sprites/8.png
tcgame/envs/assets/sprites/9.png
tcgame/envs/assets/sprites/background-day.png
tcgame/envs/assets/sprites/background-night.png
tcgame/envs/assets/sprites/base.png
tcgame/envs/assets/sprites/bluebird-downflap.png
tcgame/envs/assets/sprites/bluebird-midflap.png
tcgame-1.0.1.dist-info/LICENSE
tcgame-1.0.1.dist-info/METADATA
tcgame-1.0.1.dist-info/WHEEL
tcgame-1.0.1.dist-info/top_level.txt
tcgame-1.0.1.dist-info/RECORD
