Metadata-Version: 2.1
Name: tcgame
Version: 1.0.1
Summary: A library with access to multiple game environments.
Home-page: https://github.com/FMengz
Author: ZhaoPJ
Author-email: zhaopj1006@foxmail.com
License: UNKNOWN
Platform: UNKNOWN
Classifier: Programming Language :: Python :: 3
Classifier: License :: OSI Approved :: MIT License
Classifier: Operating System :: OS Independent
Requires-Python: >=3.6, <3.10
Requires-Dist: Pillow
Requires-Dist: numpy
Requires-Dist: pandas
Requires-Dist: pygame
Requires-Dist: matplotlib
